kumiko/__init__.py
kumiko-0.0.1.dist-info/METADATA
kumiko-0.0.1.dist-info/WHEEL
kumiko-0.0.1.dist-info/RECORD
