Metadata-Version: 2.1
Name: kumiko
Version: 0.0.1
Summary: A fast ipc lib for discord.py
Author: No767
Author-email: 73260931+No767@users.noreply.github.com
Requires-Python: >=3.8,<4.0
Classifier: Programming Language :: Python :: 3
Classifier: Programming Language :: Python :: 3.8
Classifier: Programming Language :: Python :: 3.9
Classifier: Programming Language :: Python :: 3.10
Classifier: Programming Language :: Python :: 3.11
